caerp_payment/__init__.py
caerp_payment/archive.py
caerp_payment/database.py
caerp_payment/history.py
caerp_payment/interfaces.py
caerp_payment/models.py
caerp_payment/public.py
caerp_payment/scripts.py
caerp_payment/alembic/__init__.py
caerp_payment/alembic/env.py
caerp_payment/alembic/script.py.mako
caerp_payment/alembic/versions/5_1_2_initial_state_aaaaaaaaaaaa.py
caerp_payment/alembic/versions/5_1_4_update_endi_payment_afcf321a324d.py
caerp_payment/alembic/versions/__init__.py
caerp_payment/views/__init__.py
caerp_payment/views/archive.py
caerp_payment/views/forms.py
caerp_payment/views/history.py
caerp_payment/views/routes.py
caerp_payment/views/templates/histories.mako
caerp_payment/views/templates/history.mako
caerp_payment/views/templates/local_archive_list_item_panel.mako
caerp_payment/views/templates/local_archive_panel.mako
caerp_payment-2024.0.11.dist-info/LICENSE.txt
caerp_payment-2024.0.11.dist-info/METADATA
caerp_payment-2024.0.11.dist-info/WHEEL
caerp_payment-2024.0.11.dist-info/entry_points.txt
caerp_payment-2024.0.11.dist-info/top_level.txt
caerp_payment-2024.0.11.dist-info/RECORD
