Metadata-Version: 2.2
Name: caerp_payment
Version: 2024.0.11
Summary: caerp_payment
Home-page: https://framagit.org/caerp/caerp_payment
Author: Majerti
Author-email: equipe@majerti.fr
License: GPLv3
Keywords: web wsgi bfg pylons pyramid caerp
Classifier: License :: OSI Approved :: GNU General Public License v3 (GPLv3)
Classifier: Programming Language :: Python
Classifier: Framework :: Pyramid
Classifier: Topic :: Internet :: WWW/HTTP
Classifier: Topic :: Internet :: WWW/HTTP :: WSGI :: Application
License-File: LICENSE.txt
Provides-Extra: testing
Requires-Dist: WebTest>=1.3.1; extra == "testing"
Requires-Dist: pytest; extra == "testing"
Requires-Dist: pytest-cov; extra == "testing"
Dynamic: author
Dynamic: author-email
Dynamic: classifier
Dynamic: description
Dynamic: description-content-type
Dynamic: home-page
Dynamic: keywords
Dynamic: license
Dynamic: provides-extra
Dynamic: summary
